modelisationL2tours.py
modelisationl2tours-0.4.dist-info/LICENSE
modelisationl2tours-0.4.dist-info/WHEEL
modelisationl2tours-0.4.dist-info/METADATA
modelisationl2tours-0.4.dist-info/RECORD
