Metadata-Version: 2.1
Name: modelisationL2tours
Version: 0.4
Summary: Package pour cours de modélisation L2 Tours
Author-email: arnaud-ma <84045859+arnaud-ma@sers.noreply.github.com>
Classifier: License :: OSI Approved :: MIT License
Project-URL: Home, https://github.com/arnaud-ma/modelisationL2
